tapesprocketdesigner/__init__.py
tapesprocketdesigner/designer.py
tapesprocketdesigner-0.1.11.dist-info/LICENSE
tapesprocketdesigner-0.1.11.dist-info/METADATA
tapesprocketdesigner-0.1.11.dist-info/WHEEL
tapesprocketdesigner-0.1.11.dist-info/entry_points.txt
tapesprocketdesigner-0.1.11.dist-info/top_level.txt
tapesprocketdesigner-0.1.11.dist-info/RECORD
