Metadata-Version: 2.1
Name: tapesprocketdesigner
Version: 0.1.11
Summary: An application to design SMD tape sprockets
Author-email: Niels Moseley <sofascener@gmail.com>
License: GNU GENERAL PUBLIC LICENSE
Project-URL: Homepage, https://github.com/trcwm/tapesprocketdesigner
Project-URL: Bug Tracker, https://github.com/trcwm/tapesprocketdesigner/issues
Classifier: Development Status :: 4 - Beta
Classifier: Programming Language :: Python :: 3
Classifier: License :: OSI Approved :: GNU General Public License v3 (GPLv3)
Classifier: Operating System :: OS Independent
Requires-Python: >=3.7
License-File: LICENSE
Requires-Dist: pyside6
Requires-Dist: ezdxf
